citeproc_markdown/__init__.py
citeproc_markdown/citeproc.py
citeproc_markdown-0.1.dist-info/LICENSE
citeproc_markdown-0.1.dist-info/METADATA
citeproc_markdown-0.1.dist-info/WHEEL
citeproc_markdown-0.1.dist-info/entry_points.txt
citeproc_markdown-0.1.dist-info/top_level.txt
citeproc_markdown-0.1.dist-info/RECORD
