Metadata-Version: 2.1
Name: citeproc-markdown
Version: 0.1
Summary: Citeproc extension for Python markdown
Home-page: UNKNOWN
Author: André van Delft
Author-email: andre@delve.nu
License: UNKNOWN
Platform: UNKNOWN
Classifier: Development Status :: 4 - Beta
Classifier: Programming Language :: Python :: 3
Requires-Dist: pyyaml
Requires-Dist: requests
Requires-Dist: ratelimit
Requires-Dist: markdown
